CHANGELOG.txt
LICENSE.txt
MANIFEST.in
README.md
README.txt
setup.py
priorityY/__init__.py
priorityY.egg-info/PKG-INFO
priorityY.egg-info/SOURCES.txt
priorityY.egg-info/dependency_links.txt
priorityY.egg-info/top_level.txt
venv/bin/activate_this.py
venv/lib/python3.7/site-packages/_virtualenv.py
venv/lib/python3.7/site-packages/_distutils_hack/__init__.py
venv/lib/python3.7/site-packages/_distutils_hack/override.py
venv/lib/python3.7/site-packages/pip/__init__.py
venv/lib/python3.7/site-packages/pip/__main__.py
venv/lib/python3.7/site-packages/pip-21.3.1.dist-info/LICENSE.txt
venv/lib/python3.7/site-packages/pip-21.3.1.dist-info/entry_points.txt
venv/lib/python3.7/site-packages/pip-21.3.1.dist-info/top_level.txt
venv/lib/python3.7/site-packages/pip/_internal/__init__.py
venv/lib/python3.7/site-packages/pip/_internal/build_env.py
venv/lib/python3.7/site-packages/pip/_internal/cache.py
venv/lib/python3.7/site-packages/pip/_internal/configuration.py
venv/lib/python3.7/site-packages/pip/_internal/exceptions.py
venv/lib/python3.7/site-packages/pip/_internal/main.py
venv/lib/python3.7/site-packages/pip/_internal/pyproject.py
venv/lib/python3.7/site-packages/pip/_internal/self_outdated_check.py
venv/lib/python3.7/site-packages/pip/_internal/wheel_builder.py
venv/lib/python3.7/site-packages/pip/_internal/cli/__init__.py
venv/lib/python3.7/site-packages/pip/_internal/cli/autocompletion.py
venv/lib/python3.7/site-packages/pip/_internal/cli/base_command.py
venv/lib/python3.7/site-packages/pip/_internal/cli/cmdoptions.py
venv/lib/python3.7/site-packages/pip/_internal/cli/command_context.py
venv/lib/python3.7/site-packages/pip/_internal/cli/main.py
venv/lib/python3.7/site-packages/pip/_internal/cli/main_parser.py
venv/lib/python3.7/site-packages/pip/_internal/cli/parser.py
venv/lib/python3.7/site-packages/pip/_internal/cli/progress_bars.py
venv/lib/python3.7/site-packages/pip/_internal/cli/req_command.py
venv/lib/python3.7/site-packages/pip/_internal/cli/spinners.py
venv/lib/python3.7/site-packages/pip/_internal/cli/status_codes.py
venv/lib/python3.7/site-packages/pip/_internal/commands/__init__.py
venv/lib/python3.7/site-packages/pip/_internal/commands/cache.py
venv/lib/python3.7/site-packages/pip/_internal/commands/check.py
venv/lib/python3.7/site-packages/pip/_internal/commands/completion.py
venv/lib/python3.7/site-packages/setuptools-58.4.0.dist-info/entry_points.txt
venv/lib/python3.7/site-packages/setuptools-58.4.0.dist-info/top_level.txt
venv/lib/python3.7/site-packages/wheel-0.37.0.dist-info/LICENSE.txt
venv/lib/python3.7/site-packages/wheel-0.37.0.dist-info/entry_points.txt
venv/lib/python3.7/site-packages/wheel-0.37.0.dist-info/top_level.txt
