Metadata-Version: 2.1
Name: priorityY
Version: 0.0.2
Summary: Priority Based Connected Components
Home-page: UNKNOWN
Author: Abhishek Mungoli, Pravesh Garg, Somedip Karmakar
Author-email: Abhishek.Mungoli@walmart.com, Pravesh.Garg@walmart.com, Somedip.Karmakar@walmart.com
License: MIT
Keywords: Connected Components
Platform: UNKNOWN
Classifier: Development Status :: 5 - Production/Stable
Classifier: Intended Audience :: Education
Classifier: Operating System :: Microsoft :: Windows :: Windows 10
Classifier: License :: OSI Approved :: MIT License
Classifier: Programming Language :: Python :: 3
